plydata/__init__.py
plydata/_version.py
plydata/cat_tools.py
plydata/dict.py
plydata/eval.py
plydata/expressions.py
plydata/helper_verbs.py
plydata/one_table_verbs.py
plydata/operators.py
plydata/options.py
plydata/two_table_verbs.py
plydata/types.py
plydata/utils.py
plydata/data/__init__.py
plydata/data/fishdata.csv
plydata/data/gss_cat.csv
plydata/dataframe/__init__.py
plydata/dataframe/common.py
plydata/dataframe/helpers.py
plydata/dataframe/one_table.py
plydata/dataframe/two_table.py
plydata/tests/__init__.py
plydata/tests/test_cat_tools.py
plydata/tests/test_dataframe.py
plydata/tests/test_dict.py
plydata/tests/test_expressions.py
plydata/tests/test_operators.py
plydata/tests/test_options.py
plydata/tests/test_types.py
plydata/tests/test_utils.py
plydata/tidy/__init__.py
plydata/tidy/tidy_verbs.py
plydata/tidy/dataframe/__init__.py
plydata/tidy/dataframe/tidy.py
plydata/tidy/tests/__init__.py
plydata/tidy/tests/test_tidy.py
plydata-0.4.3.dist-info/LICENSE
plydata-0.4.3.dist-info/METADATA
plydata-0.4.3.dist-info/WHEEL
plydata-0.4.3.dist-info/top_level.txt
plydata-0.4.3.dist-info/RECORD
